package_version_check_mcp/__init__.py
package_version_check_mcp/get_github_actions_pkg/__init__.py
package_version_check_mcp/get_github_actions_pkg/functions.py
package_version_check_mcp/get_github_actions_pkg/structs.py
package_version_check_mcp/get_latest_tools_pkg/__init__.py
package_version_check_mcp/get_latest_tools_pkg/functions.py
package_version_check_mcp/get_latest_tools_pkg/structs.py
package_version_check_mcp/get_latest_versions_pkg/__init__.py
package_version_check_mcp/get_latest_versions_pkg/dispatcher.py
package_version_check_mcp/get_latest_versions_pkg/fetchers/__init__.py
package_version_check_mcp/get_latest_versions_pkg/fetchers/docker.py
package_version_check_mcp/get_latest_versions_pkg/fetchers/go.py
package_version_check_mcp/get_latest_versions_pkg/fetchers/helm.py
package_version_check_mcp/get_latest_versions_pkg/fetchers/maven.py
package_version_check_mcp/get_latest_versions_pkg/fetchers/npm.py
package_version_check_mcp/get_latest_versions_pkg/fetchers/nuget.py
package_version_check_mcp/get_latest_versions_pkg/fetchers/php.py
package_version_check_mcp/get_latest_versions_pkg/fetchers/pypi.py
package_version_check_mcp/get_latest_versions_pkg/fetchers/terraform.py
package_version_check_mcp/get_latest_versions_pkg/structs.py
package_version_check_mcp/get_latest_versions_pkg/utils/__init__.py
package_version_check_mcp/get_latest_versions_pkg/utils/version_parser.py
package_version_check_mcp/main.py
package_version_check_mcp-0.0.5.dist-info/METADATA
package_version_check_mcp-0.0.5.dist-info/WHEEL
package_version_check_mcp-0.0.5.dist-info/entry_points.txt
package_version_check_mcp-0.0.5.dist-info/licenses/LICENSE
package_version_check_mcp-0.0.5.dist-info/RECORD
