Metadata-Version: 2.4
Name: package-version-check-mcp
Version: 0.0.5
Summary: A MCP server that returns the current, up-to-date version of packages you use as dependencies in a variety of ecosystems, such as Python, NPM, Go, or GitHub Actions
License-Expression: Apache-2.0
License-File: LICENSE
Author: Marius Shekow
Requires-Python: >=3.12,<4.0
Classifier: Development Status :: 3 - Alpha
Classifier: Intended Audience :: Developers
Classifier: Programming Language :: Python :: 3
Classifier: Programming Language :: Python :: 3.12
Classifier: Topic :: Software Development :: Libraries :: Python Modules
Provides-Extra: dev
Requires-Dist: docker-registry-client-async (==1.0.3)
Requires-Dist: fastmcp (==2.14.4)
Requires-Dist: httpx (==0.28.1)
Requires-Dist: pytest (==9.0.2) ; extra == "dev"
Requires-Dist: pytest-asyncio (==1.3.0) ; extra == "dev"
Requires-Dist: pyyaml (==6.0.3)
Requires-Dist: testcontainers (==4.14.0) ; extra == "dev"
Project-URL: Homepage, https://github.com/MShekow/package-version-check-mcp
Project-URL: Issues, https://github.com/MShekow/package-version-check-mcp/issues
Project-URL: Repository, https://github.com/MShekow/package-version-check-mcp
